alien_invasion/alien.py
alien_invasion/alien_invasion.py
alien_invasion/bullet.py
alien_invasion/button.py
alien_invasion/game_functions.py
alien_invasion/game_stats.py
alien_invasion/scoreboard.py
alien_invasion/settings.py
alien_invasion/ship.py
alien_invasion_spbe/alien.py
alien_invasion_spbe/alien_invasion.py
alien_invasion_spbe/bullet.py
alien_invasion_spbe/button.py
alien_invasion_spbe/game_functions.py
alien_invasion_spbe/game_stats.py
alien_invasion_spbe/scoreboard.py
alien_invasion_spbe/settings.py
alien_invasion_spbe/ship.py
alien_invasion_spbe-1.0.dist-info/LICENSE.txt
alien_invasion_spbe-1.0.dist-info/METADATA
alien_invasion_spbe-1.0.dist-info/WHEEL
alien_invasion_spbe-1.0.dist-info/entry_points.txt
alien_invasion_spbe-1.0.dist-info/top_level.txt
alien_invasion_spbe-1.0.dist-info/RECORD
