Metadata-Version: 2.1
Name: alien-invasion-spbe
Version: 1.0
Summary: A space invaders type game for shooting down aliens
Home-page: https://github.com/Javataru/python_alien_game
Author: Jeffrey Michael Brown
Author-email: jbrown5331@yandex.com
License: MIT
Platform: UNKNOWN
Classifier: License :: OSI Approved :: MIT License
Classifier: Programming Language :: Python :: 3
Classifier: Programming Language :: Python :: 3.7
Requires-Dist: pygame
